setup_badge/__init__.py
setup_badge/__main__.py
setup_badge/run.py
setup_badge-1.1.18.dist-info/licenses/LICENSE
setup_badge-1.1.18.dist-info/METADATA
setup_badge-1.1.18.dist-info/WHEEL
setup_badge-1.1.18.dist-info/entry_points.txt
setup_badge-1.1.18.dist-info/top_level.txt
setup_badge-1.1.18.dist-info/RECORD
